{
  "updated_at": "2025-09-06T15:24:28.008Z",
  "central_league": {
    "standings": [
      {
        "team_id": 2,
        "team_abbreviation": "HAN",
        "team_name": "阪神タイガース",
        "league": "Central",
        "games_played": 124,
        "wins": 76,
        "losses": 45,
        "draws": 3,
        "runs_scored": 431,
        "runs_allowed": 295,
        "win_percentage": 0.628099173553719,
        "run_differential": 136,
        "position_rank": 1,
        "games_behind": 0
      },
      {
        "team_id": 1,
        "team_abbreviation": "YOG",
        "team_name": "読売ジャイアンツ",
        "league": "Central",
        "games_played": 124,
        "wins": 59,
        "losses": 62,
        "draws": 3,
        "runs_scored": 382,
        "runs_allowed": 379,
        "win_percentage": 0.48760330578512395,
        "run_differential": 3,
        "position_rank": 2,
        "games_behind": 17
      },
      {
        "team_id": 3,
        "team_abbreviation": "YDB",
        "team_name": "横浜DeNAベイスターズ",
        "league": "Central",
        "games_played": 123,
        "wins": 57,
        "losses": 61,
        "draws": 5,
        "runs_scored": 411,
        "runs_allowed": 398,
        "win_percentage": 0.4830508474576271,
        "run_differential": 13,
        "position_rank": 3,
        "games_behind": 17.5
      },
      {
        "team_id": 5,
        "team_abbreviation": "CHU",
        "team_name": "中日ドラゴンズ",
        "league": "Central",
        "games_played": 123,
        "wins": 56,
        "losses": 65,
        "draws": 2,
        "runs_scored": 348,
        "runs_allowed": 384,
        "win_percentage": 0.4628099173553719,
        "run_differential": -36,
        "position_rank": 4,
        "games_behind": 20
      },
      {
        "team_id": 4,
        "team_abbreviation": "HIR",
        "team_name": "広島東洋カープ",
        "league": "Central",
        "games_played": 123,
        "wins": 54,
        "losses": 64,
        "draws": 5,
        "runs_scored": 383,
        "runs_allowed": 408,
        "win_percentage": 0.4576271186440678,
        "run_differential": -25,
        "position_rank": 5,
        "games_behind": 20.5
      },
      {
        "team_id": 6,
        "team_abbreviation": "YAK",
        "team_name": "東京ヤクルトスワローズ",
        "league": "Central",
        "games_played": 119,
        "wins": 44,
        "losses": 69,
        "draws": 6,
        "runs_scored": 348,
        "runs_allowed": 476,
        "win_percentage": 0.3893805309734513,
        "run_differential": -128,
        "position_rank": 6,
        "games_behind": 28
      }
    ]
  },
  "pacific_league": {
    "standings": [
      {
        "team_id": 7,
        "team_abbreviation": "SOF",
        "team_name": "福岡ソフトバンクホークス",
        "league": "Pacific",
        "games_played": 122,
        "wins": 74,
        "losses": 44,
        "draws": 4,
        "runs_scored": 470,
        "runs_allowed": 331,
        "win_percentage": 0.6271186440677966,
        "run_differential": 139,
        "position_rank": 1,
        "games_behind": 0
      },
      {
        "team_id": 12,
        "team_abbreviation": "NIP",
        "team_name": "北海道日本ハムファイターズ",
        "league": "Pacific",
        "games_played": 123,
        "wins": 72,
        "losses": 48,
        "draws": 3,
        "runs_scored": 465,
        "runs_allowed": 335,
        "win_percentage": 0.6,
        "run_differential": 130,
        "position_rank": 2,
        "games_behind": 3
      },
      {
        "team_id": 10,
        "team_abbreviation": "ORI",
        "team_name": "オリックスバファローズ",
        "league": "Pacific",
        "games_played": 120,
        "wins": 61,
        "losses": 56,
        "draws": 3,
        "runs_scored": 422,
        "runs_allowed": 443,
        "win_percentage": 0.5213675213675214,
        "run_differential": -21,
        "position_rank": 3,
        "games_behind": 12.5
      },
      {
        "team_id": 9,
        "team_abbreviation": "RAK",
        "team_name": "東北楽天ゴールデンイーグルス",
        "league": "Pacific",
        "games_played": 120,
        "wins": 56,
        "losses": 62,
        "draws": 2,
        "runs_scored": 376,
        "runs_allowed": 436,
        "win_percentage": 0.4745762711864407,
        "run_differential": -60,
        "position_rank": 4,
        "games_behind": 18
      },
      {
        "team_id": 11,
        "team_abbreviation": "SEI",
        "team_name": "埼玉西武ライオンズ",
        "league": "Pacific",
        "games_played": 120,
        "wins": 55,
        "losses": 62,
        "draws": 3,
        "runs_scored": 324,
        "runs_allowed": 363,
        "win_percentage": 0.4700854700854701,
        "run_differential": -39,
        "position_rank": 5,
        "games_behind": 18.5
      },
      {
        "team_id": 8,
        "team_abbreviation": "LOT",
        "team_name": "千葉ロッテマリーンズ",
        "league": "Pacific",
        "games_played": 119,
        "wins": 45,
        "losses": 71,
        "draws": 3,
        "runs_scored": 363,
        "runs_allowed": 475,
        "win_percentage": 0.3879310344827586,
        "run_differential": -112,
        "position_rank": 6,
        "games_behind": 28
      }
    ]
  }
}